mkdocs_changelog_feed_plugin/__init__.py
mkdocs_changelog_feed_plugin/changelog_feed.py
mkdocs_changelog_feed_plugin/tests/__init__.py
mkdocs_changelog_feed_plugin/tests/docs/CHANGELOG.md
mkdocs_changelog_feed_plugin/tests/docs/index.md
mkdocs_changelog_feed_plugin/tests/mkdocs.yaml
mkdocs_changelog_feed_plugin/tests/test_changelog_feed.py
mkdocs_changelog_feed_plugin-2025.10.24.dist-info/entry_points.txt
mkdocs_changelog_feed_plugin-2025.10.24.dist-info/licenses/LICENSE
mkdocs_changelog_feed_plugin-2025.10.24.dist-info/METADATA
mkdocs_changelog_feed_plugin-2025.10.24.dist-info/WHEEL
mkdocs_changelog_feed_plugin-2025.10.24.dist-info/RECORD
