Metadata-Version: 2.4
Name: mkdocs-changelog-feed-plugin
Version: 2025.10.24
Summary: MkDocs plugin that adds RSS and Atom feeds for a changelog in the Keep a Changelog format.
License-Expression: AGPL-3.0-or-later
License-File: LICENSE
Author: Tobias Bölz
Author-email: tobias@boelz.eu
Requires-Python: >=3.10,<4.0
Classifier: Environment :: Console
Classifier: Environment :: Web Environment
Classifier: Intended Audience :: Developers
Classifier: Operating System :: OS Independent
Classifier: Programming Language :: Python
Classifier: Programming Language :: Python :: 3
Classifier: Programming Language :: Python :: 3.10
Classifier: Programming Language :: Python :: 3.11
Classifier: Programming Language :: Python :: 3.12
Classifier: Programming Language :: Python :: 3.13
Classifier: Programming Language :: Python :: 3.14
Classifier: Programming Language :: Python :: 3 :: Only
Classifier: Topic :: Documentation
Classifier: Topic :: Text Processing
Classifier: Framework :: MkDocs
Requires-Dist: beautifulsoup4 (>=4.14.2,<5.0.0)
Requires-Dist: feedgenerator (>=2.2.1,<3.0.0)
Requires-Dist: mkdocs (>=1.6)
Project-URL: Changelog, https://tmb.codeberg.page/mkdocs-changelog-feed-plugin/changelog/
Project-URL: Documentation, https://tmb.codeberg.page/mkdocs-changelog-feed-plugin/
Project-URL: Homepage, https://tmb.codeberg.page/mkdocs-changelog-feed-plugin/
Project-URL: Issues, https://git.boelz.eu/tmb/mkdocs-changelog-feed-plugin/issues
Project-URL: Repository, https://git.boelz.eu/tmb/mkdocs-changelog-feed-plugin
